[
  {
    "assessment_date": "2026-05-15",
    "assessment_type": "Weekly Wound Information Sheet",
    "assessment_type_description": "Annual",
    "completion_date": "2026-05-15",
    "id": 167,
    "is_current": true,
    "org_id": "org_facility_b",
    "patient_id": 167,
    "pcc_assessment_id": 55167,
    "raw_json": "{\"assessmentId\": 55167, \"assessmentDate\": \"2026-05-15\", \"status\": \"Complete\", \"sections\": [{\"sectionName\": \"WOUND_INFO\", \"questions\": [{\"question\": \"Wound narrative\", \"answer\": \"Pressure Ulcer to Left heel / Measures 4.7 cm x 3.7 cm / Stage: Stage 4 / Drainage: serosanguineous, heavy\"}]}]}",
    "status": "Complete",
    "sync_version": 1,
    "template_id": 1
  }
]
