[
  {
    "created_by": "d.espinoza",
    "effective_date": "2026-05-09T04:40:00",
    "id": 16,
    "is_current": true,
    "note_label": null,
    "note_text": "*Envive Care Conference Review - V 4.0\nWound Status: Pressure Ulcer to Sacral region / Measures 1.2 cm x 1.5 cm / Stage: Stage 2\nDrainage present - serous, light. No odor noted. Treatment: Foam dressing change daily.",
    "note_type": "Wound (IDT)",
    "org_id": "org_facility_a",
    "patient_id": 11,
    "pcc_note_id": 96540,
    "sync_version": 1
  }
]
