[
  {
    "assessment_date": "2026-05-15",
    "assessment_type": "Weekly Wound Information Sheet",
    "assessment_type_description": "Quarterly",
    "completion_date": "2026-05-15",
    "id": 12,
    "is_current": true,
    "org_id": "org_facility_a",
    "patient_id": 12,
    "pcc_assessment_id": 55012,
    "raw_json": "{\"assessmentId\": 55012, \"assessmentDate\": \"2026-05-15\", \"status\": \"Complete\", \"sections\": [{\"sectionName\": \"LOCATION\", \"questions\": [{\"question\": \"Location\", \"answer\": \"Right cervical\"}, {\"question\": \"Laterality\", \"answer\": \"N/A\"}]}, {\"sectionName\": \"WOUND\", \"questions\": [{\"question\": \"Wound Type\", \"answer\": \"Abscess\"}, {\"question\": \"Stage\", \"answer\": \"N/A\"}, {\"question\": \"Length (cm)\", \"answer\": \"1.2\"}, {\"question\": \"Width (cm)\", \"answer\": \"0.7\"}, {\"question\": \"Depth (cm)\", \"answer\": \"0.2\"}]}, {\"sectionName\": \"DRAINAGE\", \"questions\": [{\"question\": \"Drainage Present\", \"answer\": \"Yes\"}, {\"question\": \"Drainage Type\", \"answer\": \"Serosanguineous\"}, {\"question\": \"Drainage Amount\", \"answer\": \"Moderate\"}]}, {\"sectionName\": \"WOUND_BED\", \"questions\": [{\"question\": \"Granulation %\", \"answer\": \"61\"}, {\"question\": \"Slough %\", \"answer\": \"37\"}, {\"question\": \"Periwound\", \"answer\": \"Macerated\"}]}]}",
    "status": "Complete",
    "sync_version": 1,
    "template_id": 2
  }
]
